{
  "artifact_contract": "E136O_CHALLENGER_OOD_RUNTIME_REPLACEMENT_GAUNTLET",
  "base_case_count": 225,
  "conservative_guard_overrides": {
    "chunk_min_support": "raised_to_minimum_3_for_oracle_free_chunk_detection",
    "hold_held_variants": "kept_true_for_runtime",
    "reject_ambiguous_same_region": "kept_true_even_if_shadow_policy_pruned_it",
    "stable_write_order": "kept_true_for_runtime"
  },
  "decision": "e136o_challenger_ood_runtime_replacement_gauntlet_confirmed",
  "full": {
    "accuracy": 1.0,
    "ambiguous_same_region_reject_count": 1214,
    "atomic_multi_region_commit_case_count": 765,
    "atomic_write_total": 3667,
    "case_count": 7146,
    "checksum_tamper_reject_count": 2224,
    "child_check_count": 936,
    "commit_chunk_count": 174,
    "commit_multi_count": 305,
    "commit_single_count": 1868,
    "correct_count": 7146,
    "defer_count": 4799,
    "destructive_delete_count": 0,
    "direct_flow_write_reject_count": 1729,
    "held_variant_promoted_count": 0,
    "oracle_plan_feature_use_count": 0,
    "order_independence_failure_count": 0,
    "partial_write_count": 0,
    "runtime_direct_write_count": 0,
    "stale_snapshot_reject_count": 1008
  },
  "heldout": {
    "accuracy": 1.0,
    "ambiguous_same_region_reject_count": 13,
    "atomic_multi_region_commit_case_count": 13,
    "atomic_write_total": 72,
    "case_count": 75,
    "checksum_tamper_reject_count": 9,
    "child_check_count": 12,
    "commit_chunk_count": 7,
    "commit_multi_count": 3,
    "commit_single_count": 32,
    "correct_count": 75,
    "defer_count": 33,
    "destructive_delete_count": 0,
    "direct_flow_write_reject_count": 12,
    "held_variant_promoted_count": 0,
    "oracle_plan_feature_use_count": 0,
    "order_independence_failure_count": 0,
    "partial_write_count": 0,
    "runtime_direct_write_count": 0,
    "stale_snapshot_reject_count": 11
  },
  "implementation_preview_allowed": true,
  "implementation_ready": true,
  "input_e136o_accepted_mutations": 6,
  "input_e136o_accepted_prune_mutations": 4,
  "input_e136o_decision": "e136o_prep_agency_atomic_multiwrite_train_gauntlet_confirmed",
  "input_e136o_full_accuracy": 1.0,
  "next": "E136P_RUNTIME_ATOMIC_MULTIWRITE_IMPLEMENTATION_PREVIEW",
  "ood": {
    "accuracy": 1.0,
    "ambiguous_same_region_reject_count": 1180,
    "atomic_multi_region_commit_case_count": 728,
    "atomic_write_total": 3476,
    "case_count": 6921,
    "checksum_tamper_reject_count": 2190,
    "child_check_count": 900,
    "commit_chunk_count": 164,
    "commit_multi_count": 294,
    "commit_single_count": 1766,
    "correct_count": 6921,
    "defer_count": 4697,
    "destructive_delete_count": 0,
    "direct_flow_write_reject_count": 1695,
    "held_variant_promoted_count": 0,
    "oracle_plan_feature_use_count": 0,
    "order_independence_failure_count": 0,
    "partial_write_count": 0,
    "runtime_direct_write_count": 0,
    "stale_snapshot_reject_count": 974
  },
  "pass_gate": true,
  "production_apply_allowed_now": false,
  "runtime_policy": {
    "chunk_min_support": 3,
    "enable_chunk_commit": true,
    "enable_multi_write": true,
    "enable_rollback_audit_write": true,
    "enable_rollback_fallback": true,
    "hold_held_variants": true,
    "max_multi_write": 3,
    "reject_ambiguous_same_region": true,
    "reject_checksum_tamper": true,
    "reject_direct_flow_write": true,
    "reject_stale_snapshot": true,
    "require_whole_group_for_chunk": true,
    "source_policy_generation": 30,
    "stable_write_order": true
  },
  "train": {
    "accuracy": 1.0,
    "ambiguous_same_region_reject_count": 21,
    "atomic_multi_region_commit_case_count": 24,
    "atomic_write_total": 119,
    "case_count": 150,
    "checksum_tamper_reject_count": 25,
    "child_check_count": 24,
    "commit_chunk_count": 3,
    "commit_multi_count": 8,
    "commit_single_count": 70,
    "correct_count": 150,
    "defer_count": 69,
    "destructive_delete_count": 0,
    "direct_flow_write_reject_count": 22,
    "held_variant_promoted_count": 0,
    "oracle_plan_feature_use_count": 0,
    "order_independence_failure_count": 0,
    "partial_write_count": 0,
    "runtime_direct_write_count": 0,
    "stale_snapshot_reject_count": 23
  }
}
