{
  "accepted_flow_write_accuracy": 0.9345238095238095,
  "answer_correct": 0.8630952380952381,
  "avg_inspects": 4.059523809523809,
  "avg_rejected_packets": 2.4583333333333335,
  "avg_steps": 6.059523809523809,
  "binary_ingress_accuracy": 0.9802768329554044,
  "closed_loop_success": 0.7976190476190477,
  "false_ask": 0.0,
  "false_frame_commit_rate": 0.003918650793650794,
  "first_useful_evidence_action": 1.0,
  "frame_sync_accuracy": 0.9661139455782313,
  "redundant_actions": 0.42857142857142855,
  "row_count": 168,
  "split_accepted_flow_write_accuracy": {
    "adversarial_sync_decoy": 1.0,
    "continuous_bit_drop": 0.75,
    "continuous_bit_insert": 0.8571428571428571,
    "continuous_stream": 1.0,
    "packet_clean": 1.0,
    "packet_noise_10": 1.0
  },
  "split_avg_steps": {
    "adversarial_sync_decoy": 4.0,
    "continuous_bit_drop": 9.5,
    "continuous_bit_insert": 9.392857142857142,
    "continuous_stream": 4.0,
    "packet_clean": 4.0,
    "packet_noise_10": 5.464285714285714
  },
  "split_closed_loop_success": {
    "adversarial_sync_decoy": 1.0,
    "continuous_bit_drop": 0.32142857142857145,
    "continuous_bit_insert": 0.4642857142857143,
    "continuous_stream": 1.0,
    "packet_clean": 1.0,
    "packet_noise_10": 1.0
  },
  "split_false_frame_commit_rate": {
    "adversarial_sync_decoy": 0.0,
    "continuous_bit_drop": 0.007936507936507936,
    "continuous_bit_insert": 0.015575396825396826,
    "continuous_stream": 0.0,
    "packet_clean": 0.0,
    "packet_noise_10": 0.0
  },
  "split_wrong_feature_write_rate": {
    "adversarial_sync_decoy": 0.0,
    "continuous_bit_drop": 0.0,
    "continuous_bit_insert": 0.0,
    "continuous_stream": 0.0,
    "packet_clean": 0.0,
    "packet_noise_10": 0.0
  },
  "system": "multi_frame_resync_guard",
  "trace_exact": 0.7976190476190477,
  "wrong_confident_answer": 0.20238095238095238,
  "wrong_feature_write_rate": 0.0
}
