{
  "action_counts": {
    "ANSWER": 109,
    "ASK_OR_DEFER": 50,
    "ASK_PERMISSION_OR_SAFE_ALTERNATIVE": 5,
    "DIAGNOSE_BOUNDARY": 18,
    "NEXT_ACTION": 26,
    "REFUSE_OR_BOUNDARY": 67,
    "SUMMARIZE": 45
  },
  "artifact_contract": "E128_ASSISTANT_TEXT_IO_LIGHTWEIGHT_RENDER_TRAINING",
  "boundary_claim_violation_count": 0,
  "boundary_claim_violation_rate": 0.0,
  "operator_rows": 382,
  "operator_trace_invalid_count": 0,
  "operator_trace_validity": 1.0,
  "overall_action_accuracy": 1.0,
  "prompt_count": 320,
  "smoke_rows": 8,
  "source_counts": {
    "adversarial_boundary": 64,
    "e127_operator_derived": 88,
    "e127_smoke_seed": 40,
    "fineweb_derived_noise": 32,
    "repo_doc_grounded": 96
  },
  "split_action_accuracy": {
    "heldout": 1.0,
    "train": 1.0,
    "validation": 1.0
  },
  "split_counts": {
    "heldout": 96,
    "train": 160,
    "validation": 64
  },
  "unsupported_answer_count": 0,
  "unsupported_answer_rate": 0.0,
  "wrong_refusal_count": 0,
  "wrong_refusal_rate": 0.0
}