{
  "checker_failure_count": 0,
  "decision": "e27_sample_only_replay_passed",
  "failures": [],
  "passed": true,
  "run_id": "cf19745ca99d8b73",
  "sample_curve_count": 64,
  "sample_metrics": {
    "best_valid_heldout_composition_success": 1.0,
    "best_valid_system": "flow_pocket_unresolved_information_seeking_primary",
    "deterministic_replay_match_rate": 1.0,
    "run_id": "cf19745ca99d8b73",
    "sample_curve_count": 64,
    "sample_row_count": 1350,
    "sample_trace_count": 300,
    "system_count": 15
  },
  "sample_only_checker_passed": true,
  "sample_row_count": 1350,
  "sample_trace_count": 300
}
