{
  "rows": [
    {
      "action": "commit_variant",
      "case_id": "answer_format_instruction_lens::clean_primary_first_control",
      "chunk_id": null,
      "correct": true,
      "expected_action": "commit_variant",
      "expected_chunk_id": null,
      "expected_variant_id": "answer_format_instruction_lens::abstract_current_primary_e136n",
      "family": "clean_primary_first_control",
      "selected_proposal_id": "answer_format_instruction_lens::primary_first_control",
      "selected_variant_id": "answer_format_instruction_lens::abstract_current_primary_e136n",
      "unsafe_commit": false
    },
    {
      "action": "commit_variant",
      "case_id": "answer_format_instruction_lens::secondary_first_arbitration",
      "chunk_id": null,
      "correct": false,
      "expected_action": "commit_variant",
      "expected_chunk_id": null,
      "expected_variant_id": "answer_format_instruction_lens::abstract_current_primary_e136n",
      "family": "secondary_first_arbitration",
      "selected_proposal_id": "answer_format_instruction_lens::secondary_first",
      "selected_variant_id": "answer_format_instruction_lens::abstract_kernel_shadow_e136h_v1",
      "unsafe_commit": false
    },
    {
      "action": "commit_variant",
      "case_id": "answer_format_instruction_lens::unsafe_direct_write_reject",
      "chunk_id": null,
      "correct": false,
      "expected_action": "commit_variant",
      "expected_chunk_id": null,
      "expected_variant_id": "answer_format_instruction_lens::abstract_current_primary_e136n",
      "family": "unsafe_direct_write_reject",
      "selected_proposal_id": "answer_format_instruction_lens::unsafe_first",
      "selected_variant_id": "answer_format_instruction_lens::unsafe_direct_write_control",
      "unsafe_commit": true
    },
    {
      "action": "commit_variant",
      "case_id": "answer_format_instruction_lens::lineage_hold_child_check",
      "chunk_id": null,
      "correct": false,
      "expected_action": "commit_variant",
      "expected_chunk_id": null,
      "expected_variant_id": "answer_format_instruction_lens::abstract_current_primary_e136n",
      "family": "lineage_hold_child_check",
      "selected_proposal_id": "answer_format_instruction_lens::lineage_candidate_first",
      "selected_variant_id": "answer_format_instruction_lens::abstract_kernel_shadow_e136h_v1",
      "unsafe_commit": false
    },
    {
      "action": "commit_variant",
      "case_id": "assistant_comparison_evaluation_lens::clean_primary_first_control",
      "chunk_id": null,
      "correct": true,
      "expected_action": "commit_variant",
      "expected_chunk_id": null,
      "expected_variant_id": "assistant_comparison_evaluation_lens::current_primary_e136n",
      "family": "clean_primary_first_control",
      "selected_proposal_id": "assistant_comparison_evaluation_lens::primary_first_control",
      "selected_variant_id": "assistant_comparison_evaluation_lens::current_primary_e136n",
      "unsafe_commit": false
    },
    {
      "action": "commit_variant",
      "case_id": "assistant_comparison_evaluation_lens::secondary_first_arbitration",
      "chunk_id": null,
      "correct": false,
      "expected_action": "commit_variant",
      "expected_chunk_id": null,
      "expected_variant_id": "assistant_comparison_evaluation_lens::current_primary_e136n",
      "family": "secondary_first_arbitration",
      "selected_proposal_id": "assistant_comparison_evaluation_lens::secondary_first",
      "selected_variant_id": "assistant_comparison_evaluation_lens::semantic_tightened_trigger_e136h_v1",
      "unsafe_commit": false
    },
    {
      "action": "commit_variant",
      "case_id": "assistant_comparison_evaluation_lens::unsafe_direct_write_reject",
      "chunk_id": null,
      "correct": false,
      "expected_action": "commit_variant",
      "expected_chunk_id": null,
      "expected_variant_id": "assistant_comparison_evaluation_lens::current_primary_e136n",
      "family": "unsafe_direct_write_reject",
      "selected_proposal_id": "assistant_comparison_evaluation_lens::unsafe_first",
      "selected_variant_id": "assistant_comparison_evaluation_lens::unsafe_direct_write_control",
      "unsafe_commit": true
    },
    {
      "action": "commit_variant",
      "case_id": "assistant_comparison_evaluation_lens::challenger_hold_child_check",
      "chunk_id": null,
      "correct": false,
      "expected_action": "commit_variant",
      "expected_chunk_id": null,
      "expected_variant_id": "assistant_comparison_evaluation_lens::current_primary_e136n",
      "family": "challenger_hold_child_check",
      "selected_proposal_id": "assistant_comparison_evaluation_lens::cheap_challenger_first",
      "selected_variant_id": "assistant_comparison_evaluation_lens::semantic_tightened_trigger_e136h_v1",
      "unsafe_commit": false
    },
    {
      "action": "commit_variant",
      "case_id": "assistant_longform_generation_request_lens::clean_primary_first_control",
      "chunk_id": null,
      "correct": true,
      "expected_action": "commit_variant",
      "expected_chunk_id": null,
      "expected_variant_id": "assistant_longform_generation_request_lens::current_primary_e136n",
      "family": "clean_primary_first_control",
      "selected_proposal_id": "assistant_longform_generation_request_lens::primary_first_control",
      "selected_variant_id": "assistant_longform_generation_request_lens::current_primary_e136n",
      "unsafe_commit": false
    },
    {
      "action": "commit_variant",
      "case_id": "assistant_longform_generation_request_lens::secondary_first_arbitration",
      "chunk_id": null,
      "correct": false,
      "expected_action": "commit_variant",
      "expected_chunk_id": null,
      "expected_variant_id": "assistant_longform_generation_request_lens::current_primary_e136n",
      "family": "secondary_first_arbitration",
      "selected_proposal_id": "assistant_longform_generation_request_lens::secondary_first",
      "selected_variant_id": "assistant_longform_generation_request_lens::semantic_tightened_trigger_e136h_v1",
      "unsafe_commit": false
    },
    {
      "action": "commit_variant",
      "case_id": "assistant_longform_generation_request_lens::unsafe_direct_write_reject",
      "chunk_id": null,
      "correct": false,
      "expected_action": "commit_variant",
      "expected_chunk_id": null,
      "expected_variant_id": "assistant_longform_generation_request_lens::current_primary_e136n",
      "family": "unsafe_direct_write_reject",
      "selected_proposal_id": "assistant_longform_generation_request_lens::unsafe_first",
      "selected_variant_id": "assistant_longform_generation_request_lens::unsafe_direct_write_control",
      "unsafe_commit": true
    },
    {
      "action": "commit_variant",
      "case_id": "assistant_longform_generation_request_lens::challenger_hold_child_check",
      "chunk_id": null,
      "correct": false,
      "expected_action": "commit_variant",
      "expected_chunk_id": null,
      "expected_variant_id": "assistant_longform_generation_request_lens::current_primary_e136n",
      "family": "challenger_hold_child_check",
      "selected_proposal_id": "assistant_longform_generation_request_lens::cheap_challenger_first",
      "selected_variant_id": "assistant_longform_generation_request_lens::semantic_tightened_trigger_e136h_v1",
      "unsafe_commit": false
    },
    {
      "action": "commit_variant",
      "case_id": "assistant_math_text_no_solve_guard::clean_primary_first_control",
      "chunk_id": null,
      "correct": true,
      "expected_action": "commit_variant",
      "expected_chunk_id": null,
      "expected_variant_id": "assistant_math_text_no_solve_guard::current_primary_e136n",
      "family": "clean_primary_first_control",
      "selected_proposal_id": "assistant_math_text_no_solve_guard::primary_first_control",
      "selected_variant_id": "assistant_math_text_no_solve_guard::current_primary_e136n",
      "unsafe_commit": false
    },
    {
      "action": "commit_variant",
      "case_id": "assistant_math_text_no_solve_guard::secondary_first_arbitration",
      "chunk_id": null,
      "correct": false,
      "expected_action": "commit_variant",
      "expected_chunk_id": null,
      "expected_variant_id": "assistant_math_text_no_solve_guard::current_primary_e136n",
      "family": "secondary_first_arbitration",
      "selected_proposal_id": "assistant_math_text_no_solve_guard::secondary_first",
      "selected_variant_id": "assistant_math_text_no_solve_guard::semantic_tightened_trigger_e136h_v1",
      "unsafe_commit": false
    },
    {
      "action": "commit_variant",
      "case_id": "assistant_math_text_no_solve_guard::unsafe_direct_write_reject",
      "chunk_id": null,
      "correct": false,
      "expected_action": "commit_variant",
      "expected_chunk_id": null,
      "expected_variant_id": "assistant_math_text_no_solve_guard::current_primary_e136n",
      "family": "unsafe_direct_write_reject",
      "selected_proposal_id": "assistant_math_text_no_solve_guard::unsafe_first",
      "selected_variant_id": "assistant_math_text_no_solve_guard::unsafe_direct_write_control",
      "unsafe_commit": true
    },
    {
      "action": "commit_variant",
      "case_id": "assistant_math_text_no_solve_guard::challenger_hold_child_check",
      "chunk_id": null,
      "correct": false,
      "expected_action": "commit_variant",
      "expected_chunk_id": null,
      "expected_variant_id": "assistant_math_text_no_solve_guard::current_primary_e136n",
      "family": "challenger_hold_child_check",
      "selected_proposal_id": "assistant_math_text_no_solve_guard::cheap_challenger_first",
      "selected_variant_id": "assistant_math_text_no_solve_guard::semantic_tightened_trigger_e136h_v1",
      "unsafe_commit": false
    },
    {
      "action": "commit_variant",
      "case_id": "assistant_role_turn_boundary_lens::clean_primary_first_control",
      "chunk_id": null,
      "correct": true,
      "expected_action": "commit_variant",
      "expected_chunk_id": null,
      "expected_variant_id": "assistant_role_turn_boundary_lens::current_primary_e136n",
      "family": "clean_primary_first_control",
      "selected_proposal_id": "assistant_role_turn_boundary_lens::primary_first_control",
      "selected_variant_id": "assistant_role_turn_boundary_lens::current_primary_e136n",
      "unsafe_commit": false
    },
    {
      "action": "commit_variant",
      "case_id": "assistant_role_turn_boundary_lens::secondary_first_arbitration",
      "chunk_id": null,
      "correct": false,
      "expected_action": "commit_variant",
      "expected_chunk_id": null,
      "expected_variant_id": "assistant_role_turn_boundary_lens::current_primary_e136n",
      "family": "secondary_first_arbitration",
      "selected_proposal_id": "assistant_role_turn_boundary_lens::secondary_first",
      "selected_variant_id": "assistant_role_turn_boundary_lens::semantic_tightened_trigger_e136h_v1",
      "unsafe_commit": false
    },
    {
      "action": "commit_variant",
      "case_id": "assistant_role_turn_boundary_lens::unsafe_direct_write_reject",
      "chunk_id": null,
      "correct": false,
      "expected_action": "commit_variant",
      "expected_chunk_id": null,
      "expected_variant_id": "assistant_role_turn_boundary_lens::current_primary_e136n",
      "family": "unsafe_direct_write_reject",
      "selected_proposal_id": "assistant_role_turn_boundary_lens::unsafe_first",
      "selected_variant_id": "assistant_role_turn_boundary_lens::unsafe_direct_write_control",
      "unsafe_commit": true
    },
    {
      "action": "commit_variant",
      "case_id": "assistant_role_turn_boundary_lens::challenger_hold_child_check",
      "chunk_id": null,
      "correct": false,
      "expected_action": "commit_variant",
      "expected_chunk_id": null,
      "expected_variant_id": "assistant_role_turn_boundary_lens::current_primary_e136n",
      "family": "challenger_hold_child_check",
      "selected_proposal_id": "assistant_role_turn_boundary_lens::cheap_challenger_first",
      "selected_variant_id": "assistant_role_turn_boundary_lens::semantic_tightened_trigger_e136h_v1",
      "unsafe_commit": false
    },
    {
      "action": "commit_variant",
      "case_id": "assistant_safety_sensitive_domain_guard::clean_primary_first_control",
      "chunk_id": null,
      "correct": true,
      "expected_action": "commit_variant",
      "expected_chunk_id": null,
      "expected_variant_id": "assistant_safety_sensitive_domain_guard::current_primary_e136n",
      "family": "clean_primary_first_control",
      "selected_proposal_id": "assistant_safety_sensitive_domain_guard::primary_first_control",
      "selected_variant_id": "assistant_safety_sensitive_domain_guard::current_primary_e136n",
      "unsafe_commit": false
    },
    {
      "action": "commit_variant",
      "case_id": "assistant_safety_sensitive_domain_guard::secondary_first_arbitration",
      "chunk_id": null,
      "correct": false,
      "expected_action": "commit_variant",
      "expected_chunk_id": null,
      "expected_variant_id": "assistant_safety_sensitive_domain_guard::current_primary_e136n",
      "family": "secondary_first_arbitration",
      "selected_proposal_id": "assistant_safety_sensitive_domain_guard::secondary_first",
      "selected_variant_id": "assistant_safety_sensitive_domain_guard::semantic_tightened_trigger_e136h_v1",
      "unsafe_commit": false
    },
    {
      "action": "commit_variant",
      "case_id": "assistant_safety_sensitive_domain_guard::unsafe_direct_write_reject",
      "chunk_id": null,
      "correct": false,
      "expected_action": "commit_variant",
      "expected_chunk_id": null,
      "expected_variant_id": "assistant_safety_sensitive_domain_guard::current_primary_e136n",
      "family": "unsafe_direct_write_reject",
      "selected_proposal_id": "assistant_safety_sensitive_domain_guard::unsafe_first",
      "selected_variant_id": "assistant_safety_sensitive_domain_guard::unsafe_direct_write_control",
      "unsafe_commit": true
    },
    {
      "action": "commit_variant",
      "case_id": "assistant_safety_sensitive_domain_guard::challenger_hold_child_check",
      "chunk_id": null,
      "correct": false,
      "expected_action": "commit_variant",
      "expected_chunk_id": null,
      "expected_variant_id": "assistant_safety_sensitive_domain_guard::current_primary_e136n",
      "family": "challenger_hold_child_check",
      "selected_proposal_id": "assistant_safety_sensitive_domain_guard::cheap_challenger_first",
      "selected_variant_id": "assistant_safety_sensitive_domain_guard::semantic_tightened_trigger_e136h_v1",
      "unsafe_commit": false
    },
    {
      "action": "commit_variant",
      "case_id": "assistant_tir_output_error_repair_guard::clean_primary_first_control",
      "chunk_id": null,
      "correct": true,
      "expected_action": "commit_variant",
      "expected_chunk_id": null,
      "expected_variant_id": "assistant_tir_output_error_repair_guard::current_primary_e136n",
      "family": "clean_primary_first_control",
      "selected_proposal_id": "assistant_tir_output_error_repair_guard::primary_first_control",
      "selected_variant_id": "assistant_tir_output_error_repair_guard::current_primary_e136n",
      "unsafe_commit": false
    },
    {
      "action": "commit_variant",
      "case_id": "assistant_tir_output_error_repair_guard::secondary_first_arbitration",
      "chunk_id": null,
      "correct": false,
      "expected_action": "commit_variant",
      "expected_chunk_id": null,
      "expected_variant_id": "assistant_tir_output_error_repair_guard::current_primary_e136n",
      "family": "secondary_first_arbitration",
      "selected_proposal_id": "assistant_tir_output_error_repair_guard::secondary_first",
      "selected_variant_id": "assistant_tir_output_error_repair_guard::semantic_tightened_trigger_e136h_v1",
      "unsafe_commit": false
    },
    {
      "action": "commit_variant",
      "case_id": "assistant_tir_output_error_repair_guard::unsafe_direct_write_reject",
      "chunk_id": null,
      "correct": false,
      "expected_action": "commit_variant",
      "expected_chunk_id": null,
      "expected_variant_id": "assistant_tir_output_error_repair_guard::current_primary_e136n",
      "family": "unsafe_direct_write_reject",
      "selected_proposal_id": "assistant_tir_output_error_repair_guard::unsafe_first",
      "selected_variant_id": "assistant_tir_output_error_repair_guard::unsafe_direct_write_control",
      "unsafe_commit": true
    },
    {
      "action": "commit_variant",
      "case_id": "assistant_tir_output_error_repair_guard::challenger_hold_child_check",
      "chunk_id": null,
      "correct": false,
      "expected_action": "commit_variant",
      "expected_chunk_id": null,
      "expected_variant_id": "assistant_tir_output_error_repair_guard::current_primary_e136n",
      "family": "challenger_hold_child_check",
      "selected_proposal_id": "assistant_tir_output_error_repair_guard::cheap_challenger_first",
      "selected_variant_id": "assistant_tir_output_error_repair_guard::semantic_tightened_trigger_e136h_v1",
      "unsafe_commit": false
    },
    {
      "action": "commit_variant",
      "case_id": "assistant_translation_multilingual_lens::clean_primary_first_control",
      "chunk_id": null,
      "correct": true,
      "expected_action": "commit_variant",
      "expected_chunk_id": null,
      "expected_variant_id": "assistant_translation_multilingual_lens::semantic_verified_pruned_e136h_v1",
      "family": "clean_primary_first_control",
      "selected_proposal_id": "assistant_translation_multilingual_lens::primary_first_control",
      "selected_variant_id": "assistant_translation_multilingual_lens::semantic_verified_pruned_e136h_v1",
      "unsafe_commit": false
    },
    {
      "action": "commit_variant",
      "case_id": "assistant_translation_multilingual_lens::secondary_first_arbitration",
      "chunk_id": null,
      "correct": false,
      "expected_action": "commit_variant",
      "expected_chunk_id": null,
      "expected_variant_id": "assistant_translation_multilingual_lens::semantic_verified_pruned_e136h_v1",
      "family": "secondary_first_arbitration",
      "selected_proposal_id": "assistant_translation_multilingual_lens::secondary_first",
      "selected_variant_id": "assistant_translation_multilingual_lens::legacy_current_e136n",
      "unsafe_commit": false
    },
    {
      "action": "commit_variant",
      "case_id": "assistant_translation_multilingual_lens::unsafe_direct_write_reject",
      "chunk_id": null,
      "correct": false,
      "expected_action": "commit_variant",
      "expected_chunk_id": null,
      "expected_variant_id": "assistant_translation_multilingual_lens::semantic_verified_pruned_e136h_v1",
      "family": "unsafe_direct_write_reject",
      "selected_proposal_id": "assistant_translation_multilingual_lens::unsafe_first",
      "selected_variant_id": "assistant_translation_multilingual_lens::unsafe_direct_write_control",
      "unsafe_commit": true
    },
    {
      "action": "commit_variant",
      "case_id": "assistant_translation_multilingual_lens::rollback_on_primary_regression",
      "chunk_id": null,
      "correct": false,
      "expected_action": "commit_variant",
      "expected_chunk_id": null,
      "expected_variant_id": "assistant_translation_multilingual_lens::legacy_current_e136n",
      "family": "rollback_on_primary_regression",
      "selected_proposal_id": "assistant_translation_multilingual_lens::regressing_primary",
      "selected_variant_id": "assistant_translation_multilingual_lens::semantic_verified_pruned_e136h_v1",
      "unsafe_commit": false
    },
    {
      "action": "commit_variant",
      "case_id": "boxed_answer_boundary_lens::clean_primary_first_control",
      "chunk_id": null,
      "correct": true,
      "expected_action": "commit_variant",
      "expected_chunk_id": null,
      "expected_variant_id": "boxed_answer_boundary_lens::semantic_verified_pruned_e136h_v1",
      "family": "clean_primary_first_control",
      "selected_proposal_id": "boxed_answer_boundary_lens::primary_first_control",
      "selected_variant_id": "boxed_answer_boundary_lens::semantic_verified_pruned_e136h_v1",
      "unsafe_commit": false
    },
    {
      "action": "commit_variant",
      "case_id": "boxed_answer_boundary_lens::secondary_first_arbitration",
      "chunk_id": null,
      "correct": false,
      "expected_action": "commit_variant",
      "expected_chunk_id": null,
      "expected_variant_id": "boxed_answer_boundary_lens::semantic_verified_pruned_e136h_v1",
      "family": "secondary_first_arbitration",
      "selected_proposal_id": "boxed_answer_boundary_lens::secondary_first",
      "selected_variant_id": "boxed_answer_boundary_lens::legacy_current_e136n",
      "unsafe_commit": false
    },
    {
      "action": "commit_variant",
      "case_id": "boxed_answer_boundary_lens::unsafe_direct_write_reject",
      "chunk_id": null,
      "correct": false,
      "expected_action": "commit_variant",
      "expected_chunk_id": null,
      "expected_variant_id": "boxed_answer_boundary_lens::semantic_verified_pruned_e136h_v1",
      "family": "unsafe_direct_write_reject",
      "selected_proposal_id": "boxed_answer_boundary_lens::unsafe_first",
      "selected_variant_id": "boxed_answer_boundary_lens::unsafe_direct_write_control",
      "unsafe_commit": true
    },
    {
      "action": "commit_variant",
      "case_id": "boxed_answer_boundary_lens::rollback_on_primary_regression",
      "chunk_id": null,
      "correct": false,
      "expected_action": "commit_variant",
      "expected_chunk_id": null,
      "expected_variant_id": "boxed_answer_boundary_lens::legacy_current_e136n",
      "family": "rollback_on_primary_regression",
      "selected_proposal_id": "boxed_answer_boundary_lens::regressing_primary",
      "selected_variant_id": "boxed_answer_boundary_lens::semantic_verified_pruned_e136h_v1",
      "unsafe_commit": false
    },
    {
      "action": "commit_variant",
      "case_id": "code_instruction_boundary_lens::clean_primary_first_control",
      "chunk_id": null,
      "correct": true,
      "expected_action": "commit_variant",
      "expected_chunk_id": null,
      "expected_variant_id": "code_instruction_boundary_lens::current_primary_e136n",
      "family": "clean_primary_first_control",
      "selected_proposal_id": "code_instruction_boundary_lens::primary_first_control",
      "selected_variant_id": "code_instruction_boundary_lens::current_primary_e136n",
      "unsafe_commit": false
    },
    {
      "action": "commit_variant",
      "case_id": "code_instruction_boundary_lens::secondary_first_arbitration",
      "chunk_id": null,
      "correct": false,
      "expected_action": "commit_variant",
      "expected_chunk_id": null,
      "expected_variant_id": "code_instruction_boundary_lens::current_primary_e136n",
      "family": "secondary_first_arbitration",
      "selected_proposal_id": "code_instruction_boundary_lens::secondary_first",
      "selected_variant_id": "code_instruction_boundary_lens::semantic_tightened_trigger_e136h_v1",
      "unsafe_commit": false
    },
    {
      "action": "commit_variant",
      "case_id": "code_instruction_boundary_lens::unsafe_direct_write_reject",
      "chunk_id": null,
      "correct": false,
      "expected_action": "commit_variant",
      "expected_chunk_id": null,
      "expected_variant_id": "code_instruction_boundary_lens::current_primary_e136n",
      "family": "unsafe_direct_write_reject",
      "selected_proposal_id": "code_instruction_boundary_lens::unsafe_first",
      "selected_variant_id": "code_instruction_boundary_lens::unsafe_direct_write_control",
      "unsafe_commit": true
    },
    {
      "action": "commit_variant",
      "case_id": "code_instruction_boundary_lens::challenger_hold_child_check",
      "chunk_id": null,
      "correct": false,
      "expected_action": "commit_variant",
      "expected_chunk_id": null,
      "expected_variant_id": "code_instruction_boundary_lens::current_primary_e136n",
      "family": "challenger_hold_child_check",
      "selected_proposal_id": "code_instruction_boundary_lens::cheap_challenger_first",
      "selected_variant_id": "code_instruction_boundary_lens::semantic_tightened_trigger_e136h_v1",
      "unsafe_commit": false
    },
    {
      "action": "commit_variant",
      "case_id": "equation_system_alignment_lens::clean_primary_first_control",
      "chunk_id": null,
      "correct": true,
      "expected_action": "commit_variant",
      "expected_chunk_id": null,
      "expected_variant_id": "equation_system_alignment_lens::abstract_current_primary_e136n",
      "family": "clean_primary_first_control",
      "selected_proposal_id": "equation_system_alignment_lens::primary_first_control",
      "selected_variant_id": "equation_system_alignment_lens::abstract_current_primary_e136n",
      "unsafe_commit": false
    },
    {
      "action": "commit_variant",
      "case_id": "equation_system_alignment_lens::secondary_first_arbitration",
      "chunk_id": null,
      "correct": false,
      "expected_action": "commit_variant",
      "expected_chunk_id": null,
      "expected_variant_id": "equation_system_alignment_lens::abstract_current_primary_e136n",
      "family": "secondary_first_arbitration",
      "selected_proposal_id": "equation_system_alignment_lens::secondary_first",
      "selected_variant_id": "equation_system_alignment_lens::abstract_kernel_shadow_e136h_v1",
      "unsafe_commit": false
    },
    {
      "action": "commit_variant",
      "case_id": "equation_system_alignment_lens::unsafe_direct_write_reject",
      "chunk_id": null,
      "correct": false,
      "expected_action": "commit_variant",
      "expected_chunk_id": null,
      "expected_variant_id": "equation_system_alignment_lens::abstract_current_primary_e136n",
      "family": "unsafe_direct_write_reject",
      "selected_proposal_id": "equation_system_alignment_lens::unsafe_first",
      "selected_variant_id": "equation_system_alignment_lens::unsafe_direct_write_control",
      "unsafe_commit": true
    },
    {
      "action": "commit_variant",
      "case_id": "equation_system_alignment_lens::lineage_hold_child_check",
      "chunk_id": null,
      "correct": false,
      "expected_action": "commit_variant",
      "expected_chunk_id": null,
      "expected_variant_id": "equation_system_alignment_lens::abstract_current_primary_e136n",
      "family": "lineage_hold_child_check",
      "selected_proposal_id": "equation_system_alignment_lens::lineage_candidate_first",
      "selected_variant_id": "equation_system_alignment_lens::abstract_kernel_shadow_e136h_v1",
      "unsafe_commit": false
    },
    {
      "action": "commit_variant",
      "case_id": "fraction_ratio_probability_lens::clean_primary_first_control",
      "chunk_id": null,
      "correct": true,
      "expected_action": "commit_variant",
      "expected_chunk_id": null,
      "expected_variant_id": "fraction_ratio_probability_lens::abstract_current_primary_e136n",
      "family": "clean_primary_first_control",
      "selected_proposal_id": "fraction_ratio_probability_lens::primary_first_control",
      "selected_variant_id": "fraction_ratio_probability_lens::abstract_current_primary_e136n",
      "unsafe_commit": false
    },
    {
      "action": "commit_variant",
      "case_id": "fraction_ratio_probability_lens::secondary_first_arbitration",
      "chunk_id": null,
      "correct": false,
      "expected_action": "commit_variant",
      "expected_chunk_id": null,
      "expected_variant_id": "fraction_ratio_probability_lens::abstract_current_primary_e136n",
      "family": "secondary_first_arbitration",
      "selected_proposal_id": "fraction_ratio_probability_lens::secondary_first",
      "selected_variant_id": "fraction_ratio_probability_lens::abstract_kernel_shadow_e136h_v1",
      "unsafe_commit": false
    },
    {
      "action": "commit_variant",
      "case_id": "fraction_ratio_probability_lens::unsafe_direct_write_reject",
      "chunk_id": null,
      "correct": false,
      "expected_action": "commit_variant",
      "expected_chunk_id": null,
      "expected_variant_id": "fraction_ratio_probability_lens::abstract_current_primary_e136n",
      "family": "unsafe_direct_write_reject",
      "selected_proposal_id": "fraction_ratio_probability_lens::unsafe_first",
      "selected_variant_id": "fraction_ratio_probability_lens::unsafe_direct_write_control",
      "unsafe_commit": true
    },
    {
      "action": "commit_variant",
      "case_id": "fraction_ratio_probability_lens::lineage_hold_child_check",
      "chunk_id": null,
      "correct": false,
      "expected_action": "commit_variant",
      "expected_chunk_id": null,
      "expected_variant_id": "fraction_ratio_probability_lens::abstract_current_primary_e136n",
      "family": "lineage_hold_child_check",
      "selected_proposal_id": "fraction_ratio_probability_lens::lineage_candidate_first",
      "selected_variant_id": "fraction_ratio_probability_lens::abstract_kernel_shadow_e136h_v1",
      "unsafe_commit": false
    },
    {
      "action": "commit_variant",
      "case_id": "geometry_diagram_reference_guard::clean_primary_first_control",
      "chunk_id": null,
      "correct": true,
      "expected_action": "commit_variant",
      "expected_chunk_id": null,
      "expected_variant_id": "geometry_diagram_reference_guard::semantic_verified_pruned_e136h_v1",
      "family": "clean_primary_first_control",
      "selected_proposal_id": "geometry_diagram_reference_guard::primary_first_control",
      "selected_variant_id": "geometry_diagram_reference_guard::semantic_verified_pruned_e136h_v1",
      "unsafe_commit": false
    },
    {
      "action": "commit_variant",
      "case_id": "geometry_diagram_reference_guard::secondary_first_arbitration",
      "chunk_id": null,
      "correct": false,
      "expected_action": "commit_variant",
      "expected_chunk_id": null,
      "expected_variant_id": "geometry_diagram_reference_guard::semantic_verified_pruned_e136h_v1",
      "family": "secondary_first_arbitration",
      "selected_proposal_id": "geometry_diagram_reference_guard::secondary_first",
      "selected_variant_id": "geometry_diagram_reference_guard::legacy_current_e136n",
      "unsafe_commit": false
    },
    {
      "action": "commit_variant",
      "case_id": "geometry_diagram_reference_guard::unsafe_direct_write_reject",
      "chunk_id": null,
      "correct": false,
      "expected_action": "commit_variant",
      "expected_chunk_id": null,
      "expected_variant_id": "geometry_diagram_reference_guard::semantic_verified_pruned_e136h_v1",
      "family": "unsafe_direct_write_reject",
      "selected_proposal_id": "geometry_diagram_reference_guard::unsafe_first",
      "selected_variant_id": "geometry_diagram_reference_guard::unsafe_direct_write_control",
      "unsafe_commit": true
    },
    {
      "action": "commit_variant",
      "case_id": "geometry_diagram_reference_guard::rollback_on_primary_regression",
      "chunk_id": null,
      "correct": false,
      "expected_action": "commit_variant",
      "expected_chunk_id": null,
      "expected_variant_id": "geometry_diagram_reference_guard::legacy_current_e136n",
      "family": "rollback_on_primary_regression",
      "selected_proposal_id": "geometry_diagram_reference_guard::regressing_primary",
      "selected_variant_id": "geometry_diagram_reference_guard::semantic_verified_pruned_e136h_v1",
      "unsafe_commit": false
    },
    {
      "action": "commit_variant",
      "case_id": "helpful_harmless_preference_guard::clean_primary_first_control",
      "chunk_id": null,
      "correct": true,
      "expected_action": "commit_variant",
      "expected_chunk_id": null,
      "expected_variant_id": "helpful_harmless_preference_guard::semantic_verified_pruned_e136h_v1",
      "family": "clean_primary_first_control",
      "selected_proposal_id": "helpful_harmless_preference_guard::primary_first_control",
      "selected_variant_id": "helpful_harmless_preference_guard::semantic_verified_pruned_e136h_v1",
      "unsafe_commit": false
    },
    {
      "action": "commit_variant",
      "case_id": "helpful_harmless_preference_guard::secondary_first_arbitration",
      "chunk_id": null,
      "correct": false,
      "expected_action": "commit_variant",
      "expected_chunk_id": null,
      "expected_variant_id": "helpful_harmless_preference_guard::semantic_verified_pruned_e136h_v1",
      "family": "secondary_first_arbitration",
      "selected_proposal_id": "helpful_harmless_preference_guard::secondary_first",
      "selected_variant_id": "helpful_harmless_preference_guard::legacy_current_e136n",
      "unsafe_commit": false
    },
    {
      "action": "commit_variant",
      "case_id": "helpful_harmless_preference_guard::unsafe_direct_write_reject",
      "chunk_id": null,
      "correct": false,
      "expected_action": "commit_variant",
      "expected_chunk_id": null,
      "expected_variant_id": "helpful_harmless_preference_guard::semantic_verified_pruned_e136h_v1",
      "family": "unsafe_direct_write_reject",
      "selected_proposal_id": "helpful_harmless_preference_guard::unsafe_first",
      "selected_variant_id": "helpful_harmless_preference_guard::unsafe_direct_write_control",
      "unsafe_commit": true
    },
    {
      "action": "commit_variant",
      "case_id": "helpful_harmless_preference_guard::rollback_on_primary_regression",
      "chunk_id": null,
      "correct": false,
      "expected_action": "commit_variant",
      "expected_chunk_id": null,
      "expected_variant_id": "helpful_harmless_preference_guard::legacy_current_e136n",
      "family": "rollback_on_primary_regression",
      "selected_proposal_id": "helpful_harmless_preference_guard::regressing_primary",
      "selected_variant_id": "helpful_harmless_preference_guard::semantic_verified_pruned_e136h_v1",
      "unsafe_commit": false
    },
    {
      "action": "commit_variant",
      "case_id": "human_written_instruction_style_lens::clean_primary_first_control",
      "chunk_id": null,
      "correct": true,
      "expected_action": "commit_variant",
      "expected_chunk_id": null,
      "expected_variant_id": "human_written_instruction_style_lens::semantic_verified_pruned_e136h_v1",
      "family": "clean_primary_first_control",
      "selected_proposal_id": "human_written_instruction_style_lens::primary_first_control",
      "selected_variant_id": "human_written_instruction_style_lens::semantic_verified_pruned_e136h_v1",
      "unsafe_commit": false
    },
    {
      "action": "commit_variant",
      "case_id": "human_written_instruction_style_lens::secondary_first_arbitration",
      "chunk_id": null,
      "correct": false,
      "expected_action": "commit_variant",
      "expected_chunk_id": null,
      "expected_variant_id": "human_written_instruction_style_lens::semantic_verified_pruned_e136h_v1",
      "family": "secondary_first_arbitration",
      "selected_proposal_id": "human_written_instruction_style_lens::secondary_first",
      "selected_variant_id": "human_written_instruction_style_lens::legacy_current_e136n",
      "unsafe_commit": false
    },
    {
      "action": "commit_variant",
      "case_id": "human_written_instruction_style_lens::unsafe_direct_write_reject",
      "chunk_id": null,
      "correct": false,
      "expected_action": "commit_variant",
      "expected_chunk_id": null,
      "expected_variant_id": "human_written_instruction_style_lens::semantic_verified_pruned_e136h_v1",
      "family": "unsafe_direct_write_reject",
      "selected_proposal_id": "human_written_instruction_style_lens::unsafe_first",
      "selected_variant_id": "human_written_instruction_style_lens::unsafe_direct_write_control",
      "unsafe_commit": true
    },
    {
      "action": "commit_variant",
      "case_id": "human_written_instruction_style_lens::rollback_on_primary_regression",
      "chunk_id": null,
      "correct": false,
      "expected_action": "commit_variant",
      "expected_chunk_id": null,
      "expected_variant_id": "human_written_instruction_style_lens::legacy_current_e136n",
      "family": "rollback_on_primary_regression",
      "selected_proposal_id": "human_written_instruction_style_lens::regressing_primary",
      "selected_variant_id": "human_written_instruction_style_lens::semantic_verified_pruned_e136h_v1",
      "unsafe_commit": false
    },
    {
      "action": "commit_variant",
      "case_id": "instruction_task_decomposition_lens::clean_primary_first_control",
      "chunk_id": null,
      "correct": true,
      "expected_action": "commit_variant",
      "expected_chunk_id": null,
      "expected_variant_id": "instruction_task_decomposition_lens::semantic_verified_pruned_e136h_v1",
      "family": "clean_primary_first_control",
      "selected_proposal_id": "instruction_task_decomposition_lens::primary_first_control",
      "selected_variant_id": "instruction_task_decomposition_lens::semantic_verified_pruned_e136h_v1",
      "unsafe_commit": false
    },
    {
      "action": "commit_variant",
      "case_id": "instruction_task_decomposition_lens::secondary_first_arbitration",
      "chunk_id": null,
      "correct": false,
      "expected_action": "commit_variant",
      "expected_chunk_id": null,
      "expected_variant_id": "instruction_task_decomposition_lens::semantic_verified_pruned_e136h_v1",
      "family": "secondary_first_arbitration",
      "selected_proposal_id": "instruction_task_decomposition_lens::secondary_first",
      "selected_variant_id": "instruction_task_decomposition_lens::legacy_current_e136n",
      "unsafe_commit": false
    },
    {
      "action": "commit_variant",
      "case_id": "instruction_task_decomposition_lens::unsafe_direct_write_reject",
      "chunk_id": null,
      "correct": false,
      "expected_action": "commit_variant",
      "expected_chunk_id": null,
      "expected_variant_id": "instruction_task_decomposition_lens::semantic_verified_pruned_e136h_v1",
      "family": "unsafe_direct_write_reject",
      "selected_proposal_id": "instruction_task_decomposition_lens::unsafe_first",
      "selected_variant_id": "instruction_task_decomposition_lens::unsafe_direct_write_control",
      "unsafe_commit": true
    },
    {
      "action": "commit_variant",
      "case_id": "instruction_task_decomposition_lens::rollback_on_primary_regression",
      "chunk_id": null,
      "correct": false,
      "expected_action": "commit_variant",
      "expected_chunk_id": null,
      "expected_variant_id": "instruction_task_decomposition_lens::legacy_current_e136n",
      "family": "rollback_on_primary_regression",
      "selected_proposal_id": "instruction_task_decomposition_lens::regressing_primary",
      "selected_variant_id": "instruction_task_decomposition_lens::semantic_verified_pruned_e136h_v1",
      "unsafe_commit": false
    },
    {
      "action": "commit_variant",
      "case_id": "latex_display_math_block_lens::clean_primary_first_control",
      "chunk_id": null,
      "correct": true,
      "expected_action": "commit_variant",
      "expected_chunk_id": null,
      "expected_variant_id": "latex_display_math_block_lens::current_primary_e136n",
      "family": "clean_primary_first_control",
      "selected_proposal_id": "latex_display_math_block_lens::primary_first_control",
      "selected_variant_id": "latex_display_math_block_lens::current_primary_e136n",
      "unsafe_commit": false
    },
    {
      "action": "commit_variant",
      "case_id": "latex_display_math_block_lens::secondary_first_arbitration",
      "chunk_id": null,
      "correct": false,
      "expected_action": "commit_variant",
      "expected_chunk_id": null,
      "expected_variant_id": "latex_display_math_block_lens::current_primary_e136n",
      "family": "secondary_first_arbitration",
      "selected_proposal_id": "latex_display_math_block_lens::secondary_first",
      "selected_variant_id": "latex_display_math_block_lens::semantic_tightened_trigger_e136h_v1",
      "unsafe_commit": false
    },
    {
      "action": "commit_variant",
      "case_id": "latex_display_math_block_lens::unsafe_direct_write_reject",
      "chunk_id": null,
      "correct": false,
      "expected_action": "commit_variant",
      "expected_chunk_id": null,
      "expected_variant_id": "latex_display_math_block_lens::current_primary_e136n",
      "family": "unsafe_direct_write_reject",
      "selected_proposal_id": "latex_display_math_block_lens::unsafe_first",
      "selected_variant_id": "latex_display_math_block_lens::unsafe_direct_write_control",
      "unsafe_commit": true
    },
    {
      "action": "commit_variant",
      "case_id": "latex_display_math_block_lens::challenger_hold_child_check",
      "chunk_id": null,
      "correct": false,
      "expected_action": "commit_variant",
      "expected_chunk_id": null,
      "expected_variant_id": "latex_display_math_block_lens::current_primary_e136n",
      "family": "challenger_hold_child_check",
      "selected_proposal_id": "latex_display_math_block_lens::cheap_challenger_first",
      "selected_variant_id": "latex_display_math_block_lens::semantic_tightened_trigger_e136h_v1",
      "unsafe_commit": false
    },
    {
      "action": "commit_variant",
      "case_id": "latex_inline_math_boundary_lens::clean_primary_first_control",
      "chunk_id": null,
      "correct": true,
      "expected_action": "commit_variant",
      "expected_chunk_id": null,
      "expected_variant_id": "latex_inline_math_boundary_lens::semantic_verified_pruned_e136h_v1",
      "family": "clean_primary_first_control",
      "selected_proposal_id": "latex_inline_math_boundary_lens::primary_first_control",
      "selected_variant_id": "latex_inline_math_boundary_lens::semantic_verified_pruned_e136h_v1",
      "unsafe_commit": false
    },
    {
      "action": "commit_variant",
      "case_id": "latex_inline_math_boundary_lens::secondary_first_arbitration",
      "chunk_id": null,
      "correct": false,
      "expected_action": "commit_variant",
      "expected_chunk_id": null,
      "expected_variant_id": "latex_inline_math_boundary_lens::semantic_verified_pruned_e136h_v1",
      "family": "secondary_first_arbitration",
      "selected_proposal_id": "latex_inline_math_boundary_lens::secondary_first",
      "selected_variant_id": "latex_inline_math_boundary_lens::legacy_current_e136n",
      "unsafe_commit": false
    },
    {
      "action": "commit_variant",
      "case_id": "latex_inline_math_boundary_lens::unsafe_direct_write_reject",
      "chunk_id": null,
      "correct": false,
      "expected_action": "commit_variant",
      "expected_chunk_id": null,
      "expected_variant_id": "latex_inline_math_boundary_lens::semantic_verified_pruned_e136h_v1",
      "family": "unsafe_direct_write_reject",
      "selected_proposal_id": "latex_inline_math_boundary_lens::unsafe_first",
      "selected_variant_id": "latex_inline_math_boundary_lens::unsafe_direct_write_control",
      "unsafe_commit": true
    },
    {
      "action": "commit_variant",
      "case_id": "latex_inline_math_boundary_lens::rollback_on_primary_regression",
      "chunk_id": null,
      "correct": false,
      "expected_action": "commit_variant",
      "expected_chunk_id": null,
      "expected_variant_id": "latex_inline_math_boundary_lens::legacy_current_e136n",
      "family": "rollback_on_primary_regression",
      "selected_proposal_id": "latex_inline_math_boundary_lens::regressing_primary",
      "selected_variant_id": "latex_inline_math_boundary_lens::semantic_verified_pruned_e136h_v1",
      "unsafe_commit": false
    },
    {
      "action": "commit_variant",
      "case_id": "matrix_vector_block_lens::clean_primary_first_control",
      "chunk_id": null,
      "correct": true,
      "expected_action": "commit_variant",
      "expected_chunk_id": null,
      "expected_variant_id": "matrix_vector_block_lens::semantic_verified_pruned_e136h_v1",
      "family": "clean_primary_first_control",
      "selected_proposal_id": "matrix_vector_block_lens::primary_first_control",
      "selected_variant_id": "matrix_vector_block_lens::semantic_verified_pruned_e136h_v1",
      "unsafe_commit": false
    },
    {
      "action": "commit_variant",
      "case_id": "matrix_vector_block_lens::secondary_first_arbitration",
      "chunk_id": null,
      "correct": false,
      "expected_action": "commit_variant",
      "expected_chunk_id": null,
      "expected_variant_id": "matrix_vector_block_lens::semantic_verified_pruned_e136h_v1",
      "family": "secondary_first_arbitration",
      "selected_proposal_id": "matrix_vector_block_lens::secondary_first",
      "selected_variant_id": "matrix_vector_block_lens::legacy_current_e136n",
      "unsafe_commit": false
    },
    {
      "action": "commit_variant",
      "case_id": "matrix_vector_block_lens::unsafe_direct_write_reject",
      "chunk_id": null,
      "correct": false,
      "expected_action": "commit_variant",
      "expected_chunk_id": null,
      "expected_variant_id": "matrix_vector_block_lens::semantic_verified_pruned_e136h_v1",
      "family": "unsafe_direct_write_reject",
      "selected_proposal_id": "matrix_vector_block_lens::unsafe_first",
      "selected_variant_id": "matrix_vector_block_lens::unsafe_direct_write_control",
      "unsafe_commit": true
    },
    {
      "action": "commit_variant",
      "case_id": "matrix_vector_block_lens::rollback_on_primary_regression",
      "chunk_id": null,
      "correct": false,
      "expected_action": "commit_variant",
      "expected_chunk_id": null,
      "expected_variant_id": "matrix_vector_block_lens::legacy_current_e136n",
      "family": "rollback_on_primary_regression",
      "selected_proposal_id": "matrix_vector_block_lens::regressing_primary",
      "selected_variant_id": "matrix_vector_block_lens::semantic_verified_pruned_e136h_v1",
      "unsafe_commit": false
    },
    {
      "action": "commit_variant",
      "case_id": "multi_turn_context_continuity_lens::clean_primary_first_control",
      "chunk_id": null,
      "correct": true,
      "expected_action": "commit_variant",
      "expected_chunk_id": null,
      "expected_variant_id": "multi_turn_context_continuity_lens::current_primary_e136n",
      "family": "clean_primary_first_control",
      "selected_proposal_id": "multi_turn_context_continuity_lens::primary_first_control",
      "selected_variant_id": "multi_turn_context_continuity_lens::current_primary_e136n",
      "unsafe_commit": false
    },
    {
      "action": "commit_variant",
      "case_id": "multi_turn_context_continuity_lens::secondary_first_arbitration",
      "chunk_id": null,
      "correct": false,
      "expected_action": "commit_variant",
      "expected_chunk_id": null,
      "expected_variant_id": "multi_turn_context_continuity_lens::current_primary_e136n",
      "family": "secondary_first_arbitration",
      "selected_proposal_id": "multi_turn_context_continuity_lens::secondary_first",
      "selected_variant_id": "multi_turn_context_continuity_lens::semantic_tightened_trigger_e136h_v1",
      "unsafe_commit": false
    },
    {
      "action": "commit_variant",
      "case_id": "multi_turn_context_continuity_lens::unsafe_direct_write_reject",
      "chunk_id": null,
      "correct": false,
      "expected_action": "commit_variant",
      "expected_chunk_id": null,
      "expected_variant_id": "multi_turn_context_continuity_lens::current_primary_e136n",
      "family": "unsafe_direct_write_reject",
      "selected_proposal_id": "multi_turn_context_continuity_lens::unsafe_first",
      "selected_variant_id": "multi_turn_context_continuity_lens::unsafe_direct_write_control",
      "unsafe_commit": true
    },
    {
      "action": "commit_variant",
      "case_id": "multi_turn_context_continuity_lens::challenger_hold_child_check",
      "chunk_id": null,
      "correct": false,
      "expected_action": "commit_variant",
      "expected_chunk_id": null,
      "expected_variant_id": "multi_turn_context_continuity_lens::current_primary_e136n",
      "family": "challenger_hold_child_check",
      "selected_proposal_id": "multi_turn_context_continuity_lens::cheap_challenger_first",
      "selected_variant_id": "multi_turn_context_continuity_lens::semantic_tightened_trigger_e136h_v1",
      "unsafe_commit": false
    },
    {
      "action": "commit_variant",
      "case_id": "piecewise_case_function_lens::clean_primary_first_control",
      "chunk_id": null,
      "correct": true,
      "expected_action": "commit_variant",
      "expected_chunk_id": null,
      "expected_variant_id": "piecewise_case_function_lens::abstract_current_primary_e136n",
      "family": "clean_primary_first_control",
      "selected_proposal_id": "piecewise_case_function_lens::primary_first_control",
      "selected_variant_id": "piecewise_case_function_lens::abstract_current_primary_e136n",
      "unsafe_commit": false
    },
    {
      "action": "commit_variant",
      "case_id": "piecewise_case_function_lens::secondary_first_arbitration",
      "chunk_id": null,
      "correct": false,
      "expected_action": "commit_variant",
      "expected_chunk_id": null,
      "expected_variant_id": "piecewise_case_function_lens::abstract_current_primary_e136n",
      "family": "secondary_first_arbitration",
      "selected_proposal_id": "piecewise_case_function_lens::secondary_first",
      "selected_variant_id": "piecewise_case_function_lens::abstract_kernel_shadow_e136h_v1",
      "unsafe_commit": false
    },
    {
      "action": "commit_variant",
      "case_id": "piecewise_case_function_lens::unsafe_direct_write_reject",
      "chunk_id": null,
      "correct": false,
      "expected_action": "commit_variant",
      "expected_chunk_id": null,
      "expected_variant_id": "piecewise_case_function_lens::abstract_current_primary_e136n",
      "family": "unsafe_direct_write_reject",
      "selected_proposal_id": "piecewise_case_function_lens::unsafe_first",
      "selected_variant_id": "piecewise_case_function_lens::unsafe_direct_write_control",
      "unsafe_commit": true
    },
    {
      "action": "commit_variant",
      "case_id": "piecewise_case_function_lens::lineage_hold_child_check",
      "chunk_id": null,
      "correct": false,
      "expected_action": "commit_variant",
      "expected_chunk_id": null,
      "expected_variant_id": "piecewise_case_function_lens::abstract_current_primary_e136n",
      "family": "lineage_hold_child_check",
      "selected_proposal_id": "piecewise_case_function_lens::lineage_candidate_first",
      "selected_variant_id": "piecewise_case_function_lens::abstract_kernel_shadow_e136h_v1",
      "unsafe_commit": false
    },
    {
      "action": "commit_variant",
      "case_id": "proof_step_connector_lens::clean_primary_first_control",
      "chunk_id": null,
      "correct": true,
      "expected_action": "commit_variant",
      "expected_chunk_id": null,
      "expected_variant_id": "proof_step_connector_lens::semantic_verified_pruned_e136h_v1",
      "family": "clean_primary_first_control",
      "selected_proposal_id": "proof_step_connector_lens::primary_first_control",
      "selected_variant_id": "proof_step_connector_lens::semantic_verified_pruned_e136h_v1",
      "unsafe_commit": false
    },
    {
      "action": "commit_variant",
      "case_id": "proof_step_connector_lens::secondary_first_arbitration",
      "chunk_id": null,
      "correct": false,
      "expected_action": "commit_variant",
      "expected_chunk_id": null,
      "expected_variant_id": "proof_step_connector_lens::semantic_verified_pruned_e136h_v1",
      "family": "secondary_first_arbitration",
      "selected_proposal_id": "proof_step_connector_lens::secondary_first",
      "selected_variant_id": "proof_step_connector_lens::legacy_current_e136n",
      "unsafe_commit": false
    },
    {
      "action": "commit_variant",
      "case_id": "proof_step_connector_lens::unsafe_direct_write_reject",
      "chunk_id": null,
      "correct": false,
      "expected_action": "commit_variant",
      "expected_chunk_id": null,
      "expected_variant_id": "proof_step_connector_lens::semantic_verified_pruned_e136h_v1",
      "family": "unsafe_direct_write_reject",
      "selected_proposal_id": "proof_step_connector_lens::unsafe_first",
      "selected_variant_id": "proof_step_connector_lens::unsafe_direct_write_control",
      "unsafe_commit": true
    },
    {
      "action": "commit_variant",
      "case_id": "proof_step_connector_lens::rollback_on_primary_regression",
      "chunk_id": null,
      "correct": false,
      "expected_action": "commit_variant",
      "expected_chunk_id": null,
      "expected_variant_id": "proof_step_connector_lens::legacy_current_e136n",
      "family": "rollback_on_primary_regression",
      "selected_proposal_id": "proof_step_connector_lens::regressing_primary",
      "selected_variant_id": "proof_step_connector_lens::semantic_verified_pruned_e136h_v1",
      "unsafe_commit": false
    },
    {
      "action": "commit_variant",
      "case_id": "reasoning_instruction_lens::clean_primary_first_control",
      "chunk_id": null,
      "correct": true,
      "expected_action": "commit_variant",
      "expected_chunk_id": null,
      "expected_variant_id": "reasoning_instruction_lens::semantic_verified_pruned_e136h_v1",
      "family": "clean_primary_first_control",
      "selected_proposal_id": "reasoning_instruction_lens::primary_first_control",
      "selected_variant_id": "reasoning_instruction_lens::semantic_verified_pruned_e136h_v1",
      "unsafe_commit": false
    },
    {
      "action": "commit_variant",
      "case_id": "reasoning_instruction_lens::secondary_first_arbitration",
      "chunk_id": null,
      "correct": false,
      "expected_action": "commit_variant",
      "expected_chunk_id": null,
      "expected_variant_id": "reasoning_instruction_lens::semantic_verified_pruned_e136h_v1",
      "family": "secondary_first_arbitration",
      "selected_proposal_id": "reasoning_instruction_lens::secondary_first",
      "selected_variant_id": "reasoning_instruction_lens::legacy_current_e136n",
      "unsafe_commit": false
    },
    {
      "action": "commit_variant",
      "case_id": "reasoning_instruction_lens::unsafe_direct_write_reject",
      "chunk_id": null,
      "correct": false,
      "expected_action": "commit_variant",
      "expected_chunk_id": null,
      "expected_variant_id": "reasoning_instruction_lens::semantic_verified_pruned_e136h_v1",
      "family": "unsafe_direct_write_reject",
      "selected_proposal_id": "reasoning_instruction_lens::unsafe_first",
      "selected_variant_id": "reasoning_instruction_lens::unsafe_direct_write_control",
      "unsafe_commit": true
    },
    {
      "action": "commit_variant",
      "case_id": "reasoning_instruction_lens::rollback_on_primary_regression",
      "chunk_id": null,
      "correct": false,
      "expected_action": "commit_variant",
      "expected_chunk_id": null,
      "expected_variant_id": "reasoning_instruction_lens::legacy_current_e136n",
      "family": "rollback_on_primary_regression",
      "selected_proposal_id": "reasoning_instruction_lens::regressing_primary",
      "selected_variant_id": "reasoning_instruction_lens::semantic_verified_pruned_e136h_v1",
      "unsafe_commit": false
    },
    {
      "action": "commit_variant",
      "case_id": "refusal_boundary_guard::clean_primary_first_control",
      "chunk_id": null,
      "correct": true,
      "expected_action": "commit_variant",
      "expected_chunk_id": null,
      "expected_variant_id": "refusal_boundary_guard::semantic_verified_pruned_e136h_v1",
      "family": "clean_primary_first_control",
      "selected_proposal_id": "refusal_boundary_guard::primary_first_control",
      "selected_variant_id": "refusal_boundary_guard::semantic_verified_pruned_e136h_v1",
      "unsafe_commit": false
    },
    {
      "action": "commit_variant",
      "case_id": "refusal_boundary_guard::secondary_first_arbitration",
      "chunk_id": null,
      "correct": false,
      "expected_action": "commit_variant",
      "expected_chunk_id": null,
      "expected_variant_id": "refusal_boundary_guard::semantic_verified_pruned_e136h_v1",
      "family": "secondary_first_arbitration",
      "selected_proposal_id": "refusal_boundary_guard::secondary_first",
      "selected_variant_id": "refusal_boundary_guard::legacy_current_e136n",
      "unsafe_commit": false
    },
    {
      "action": "commit_variant",
      "case_id": "refusal_boundary_guard::unsafe_direct_write_reject",
      "chunk_id": null,
      "correct": false,
      "expected_action": "commit_variant",
      "expected_chunk_id": null,
      "expected_variant_id": "refusal_boundary_guard::semantic_verified_pruned_e136h_v1",
      "family": "unsafe_direct_write_reject",
      "selected_proposal_id": "refusal_boundary_guard::unsafe_first",
      "selected_variant_id": "refusal_boundary_guard::unsafe_direct_write_control",
      "unsafe_commit": true
    },
    {
      "action": "commit_variant",
      "case_id": "refusal_boundary_guard::rollback_on_primary_regression",
      "chunk_id": null,
      "correct": false,
      "expected_action": "commit_variant",
      "expected_chunk_id": null,
      "expected_variant_id": "refusal_boundary_guard::legacy_current_e136n",
      "family": "rollback_on_primary_regression",
      "selected_proposal_id": "refusal_boundary_guard::regressing_primary",
      "selected_variant_id": "refusal_boundary_guard::semantic_verified_pruned_e136h_v1",
      "unsafe_commit": false
    },
    {
      "action": "commit_variant",
      "case_id": "rejected_response_contrast_lens::clean_primary_first_control",
      "chunk_id": null,
      "correct": true,
      "expected_action": "commit_variant",
      "expected_chunk_id": null,
      "expected_variant_id": "rejected_response_contrast_lens::semantic_verified_pruned_e136h_v1",
      "family": "clean_primary_first_control",
      "selected_proposal_id": "rejected_response_contrast_lens::primary_first_control",
      "selected_variant_id": "rejected_response_contrast_lens::semantic_verified_pruned_e136h_v1",
      "unsafe_commit": false
    },
    {
      "action": "commit_variant",
      "case_id": "rejected_response_contrast_lens::secondary_first_arbitration",
      "chunk_id": null,
      "correct": false,
      "expected_action": "commit_variant",
      "expected_chunk_id": null,
      "expected_variant_id": "rejected_response_contrast_lens::semantic_verified_pruned_e136h_v1",
      "family": "secondary_first_arbitration",
      "selected_proposal_id": "rejected_response_contrast_lens::secondary_first",
      "selected_variant_id": "rejected_response_contrast_lens::legacy_current_e136n",
      "unsafe_commit": false
    },
    {
      "action": "commit_variant",
      "case_id": "rejected_response_contrast_lens::unsafe_direct_write_reject",
      "chunk_id": null,
      "correct": false,
      "expected_action": "commit_variant",
      "expected_chunk_id": null,
      "expected_variant_id": "rejected_response_contrast_lens::semantic_verified_pruned_e136h_v1",
      "family": "unsafe_direct_write_reject",
      "selected_proposal_id": "rejected_response_contrast_lens::unsafe_first",
      "selected_variant_id": "rejected_response_contrast_lens::unsafe_direct_write_control",
      "unsafe_commit": true
    },
    {
      "action": "commit_variant",
      "case_id": "rejected_response_contrast_lens::rollback_on_primary_regression",
      "chunk_id": null,
      "correct": false,
      "expected_action": "commit_variant",
      "expected_chunk_id": null,
      "expected_variant_id": "rejected_response_contrast_lens::legacy_current_e136n",
      "family": "rollback_on_primary_regression",
      "selected_proposal_id": "rejected_response_contrast_lens::regressing_primary",
      "selected_variant_id": "rejected_response_contrast_lens::semantic_verified_pruned_e136h_v1",
      "unsafe_commit": false
    },
    {
      "action": "commit_variant",
      "case_id": "response_format_constraint_lens::clean_primary_first_control",
      "chunk_id": null,
      "correct": true,
      "expected_action": "commit_variant",
      "expected_chunk_id": null,
      "expected_variant_id": "response_format_constraint_lens::current_primary_e136n",
      "family": "clean_primary_first_control",
      "selected_proposal_id": "response_format_constraint_lens::primary_first_control",
      "selected_variant_id": "response_format_constraint_lens::current_primary_e136n",
      "unsafe_commit": false
    },
    {
      "action": "commit_variant",
      "case_id": "response_format_constraint_lens::secondary_first_arbitration",
      "chunk_id": null,
      "correct": false,
      "expected_action": "commit_variant",
      "expected_chunk_id": null,
      "expected_variant_id": "response_format_constraint_lens::current_primary_e136n",
      "family": "secondary_first_arbitration",
      "selected_proposal_id": "response_format_constraint_lens::secondary_first",
      "selected_variant_id": "response_format_constraint_lens::semantic_tightened_trigger_e136h_v1",
      "unsafe_commit": false
    },
    {
      "action": "commit_variant",
      "case_id": "response_format_constraint_lens::unsafe_direct_write_reject",
      "chunk_id": null,
      "correct": false,
      "expected_action": "commit_variant",
      "expected_chunk_id": null,
      "expected_variant_id": "response_format_constraint_lens::current_primary_e136n",
      "family": "unsafe_direct_write_reject",
      "selected_proposal_id": "response_format_constraint_lens::unsafe_first",
      "selected_variant_id": "response_format_constraint_lens::unsafe_direct_write_control",
      "unsafe_commit": true
    },
    {
      "action": "commit_variant",
      "case_id": "response_format_constraint_lens::challenger_hold_child_check",
      "chunk_id": null,
      "correct": false,
      "expected_action": "commit_variant",
      "expected_chunk_id": null,
      "expected_variant_id": "response_format_constraint_lens::current_primary_e136n",
      "family": "challenger_hold_child_check",
      "selected_proposal_id": "response_format_constraint_lens::cheap_challenger_first",
      "selected_variant_id": "response_format_constraint_lens::semantic_tightened_trigger_e136h_v1",
      "unsafe_commit": false
    },
    {
      "action": "commit_variant",
      "case_id": "source_absence_defer_guard::clean_primary_first_control",
      "chunk_id": null,
      "correct": true,
      "expected_action": "commit_variant",
      "expected_chunk_id": null,
      "expected_variant_id": "source_absence_defer_guard::semantic_verified_pruned_e136h_v1",
      "family": "clean_primary_first_control",
      "selected_proposal_id": "source_absence_defer_guard::primary_first_control",
      "selected_variant_id": "source_absence_defer_guard::semantic_verified_pruned_e136h_v1",
      "unsafe_commit": false
    },
    {
      "action": "commit_variant",
      "case_id": "source_absence_defer_guard::secondary_first_arbitration",
      "chunk_id": null,
      "correct": false,
      "expected_action": "commit_variant",
      "expected_chunk_id": null,
      "expected_variant_id": "source_absence_defer_guard::semantic_verified_pruned_e136h_v1",
      "family": "secondary_first_arbitration",
      "selected_proposal_id": "source_absence_defer_guard::secondary_first",
      "selected_variant_id": "source_absence_defer_guard::legacy_current_e136n",
      "unsafe_commit": false
    },
    {
      "action": "commit_variant",
      "case_id": "source_absence_defer_guard::unsafe_direct_write_reject",
      "chunk_id": null,
      "correct": false,
      "expected_action": "commit_variant",
      "expected_chunk_id": null,
      "expected_variant_id": "source_absence_defer_guard::semantic_verified_pruned_e136h_v1",
      "family": "unsafe_direct_write_reject",
      "selected_proposal_id": "source_absence_defer_guard::unsafe_first",
      "selected_variant_id": "source_absence_defer_guard::unsafe_direct_write_control",
      "unsafe_commit": true
    },
    {
      "action": "commit_variant",
      "case_id": "source_absence_defer_guard::rollback_on_primary_regression",
      "chunk_id": null,
      "correct": false,
      "expected_action": "commit_variant",
      "expected_chunk_id": null,
      "expected_variant_id": "source_absence_defer_guard::legacy_current_e136n",
      "family": "rollback_on_primary_regression",
      "selected_proposal_id": "source_absence_defer_guard::regressing_primary",
      "selected_variant_id": "source_absence_defer_guard::semantic_verified_pruned_e136h_v1",
      "unsafe_commit": false
    },
    {
      "action": "commit_variant",
      "case_id": "summarization_request_lens::clean_primary_first_control",
      "chunk_id": null,
      "correct": true,
      "expected_action": "commit_variant",
      "expected_chunk_id": null,
      "expected_variant_id": "summarization_request_lens::semantic_verified_pruned_e136h_v1",
      "family": "clean_primary_first_control",
      "selected_proposal_id": "summarization_request_lens::primary_first_control",
      "selected_variant_id": "summarization_request_lens::semantic_verified_pruned_e136h_v1",
      "unsafe_commit": false
    },
    {
      "action": "commit_variant",
      "case_id": "summarization_request_lens::secondary_first_arbitration",
      "chunk_id": null,
      "correct": false,
      "expected_action": "commit_variant",
      "expected_chunk_id": null,
      "expected_variant_id": "summarization_request_lens::semantic_verified_pruned_e136h_v1",
      "family": "secondary_first_arbitration",
      "selected_proposal_id": "summarization_request_lens::secondary_first",
      "selected_variant_id": "summarization_request_lens::legacy_current_e136n",
      "unsafe_commit": false
    },
    {
      "action": "commit_variant",
      "case_id": "summarization_request_lens::unsafe_direct_write_reject",
      "chunk_id": null,
      "correct": false,
      "expected_action": "commit_variant",
      "expected_chunk_id": null,
      "expected_variant_id": "summarization_request_lens::semantic_verified_pruned_e136h_v1",
      "family": "unsafe_direct_write_reject",
      "selected_proposal_id": "summarization_request_lens::unsafe_first",
      "selected_variant_id": "summarization_request_lens::unsafe_direct_write_control",
      "unsafe_commit": true
    },
    {
      "action": "commit_variant",
      "case_id": "summarization_request_lens::rollback_on_primary_regression",
      "chunk_id": null,
      "correct": false,
      "expected_action": "commit_variant",
      "expected_chunk_id": null,
      "expected_variant_id": "summarization_request_lens::legacy_current_e136n",
      "family": "rollback_on_primary_regression",
      "selected_proposal_id": "summarization_request_lens::regressing_primary",
      "selected_variant_id": "summarization_request_lens::semantic_verified_pruned_e136h_v1",
      "unsafe_commit": false
    },
    {
      "action": "commit_variant",
      "case_id": "summation_sequence_series_lens::clean_primary_first_control",
      "chunk_id": null,
      "correct": true,
      "expected_action": "commit_variant",
      "expected_chunk_id": null,
      "expected_variant_id": "summation_sequence_series_lens::abstract_current_primary_e136n",
      "family": "clean_primary_first_control",
      "selected_proposal_id": "summation_sequence_series_lens::primary_first_control",
      "selected_variant_id": "summation_sequence_series_lens::abstract_current_primary_e136n",
      "unsafe_commit": false
    },
    {
      "action": "commit_variant",
      "case_id": "summation_sequence_series_lens::secondary_first_arbitration",
      "chunk_id": null,
      "correct": false,
      "expected_action": "commit_variant",
      "expected_chunk_id": null,
      "expected_variant_id": "summation_sequence_series_lens::abstract_current_primary_e136n",
      "family": "secondary_first_arbitration",
      "selected_proposal_id": "summation_sequence_series_lens::secondary_first",
      "selected_variant_id": "summation_sequence_series_lens::abstract_kernel_shadow_e136h_v1",
      "unsafe_commit": false
    },
    {
      "action": "commit_variant",
      "case_id": "summation_sequence_series_lens::unsafe_direct_write_reject",
      "chunk_id": null,
      "correct": false,
      "expected_action": "commit_variant",
      "expected_chunk_id": null,
      "expected_variant_id": "summation_sequence_series_lens::abstract_current_primary_e136n",
      "family": "unsafe_direct_write_reject",
      "selected_proposal_id": "summation_sequence_series_lens::unsafe_first",
      "selected_variant_id": "summation_sequence_series_lens::unsafe_direct_write_control",
      "unsafe_commit": true
    },
    {
      "action": "commit_variant",
      "case_id": "summation_sequence_series_lens::lineage_hold_child_check",
      "chunk_id": null,
      "correct": false,
      "expected_action": "commit_variant",
      "expected_chunk_id": null,
      "expected_variant_id": "summation_sequence_series_lens::abstract_current_primary_e136n",
      "family": "lineage_hold_child_check",
      "selected_proposal_id": "summation_sequence_series_lens::lineage_candidate_first",
      "selected_variant_id": "summation_sequence_series_lens::abstract_kernel_shadow_e136h_v1",
      "unsafe_commit": false
    },
    {
      "action": "commit_variant",
      "case_id": "synthetic_dialogue_noise_guard::clean_primary_first_control",
      "chunk_id": null,
      "correct": true,
      "expected_action": "commit_variant",
      "expected_chunk_id": null,
      "expected_variant_id": "synthetic_dialogue_noise_guard::semantic_verified_pruned_e136h_v1",
      "family": "clean_primary_first_control",
      "selected_proposal_id": "synthetic_dialogue_noise_guard::primary_first_control",
      "selected_variant_id": "synthetic_dialogue_noise_guard::semantic_verified_pruned_e136h_v1",
      "unsafe_commit": false
    },
    {
      "action": "commit_variant",
      "case_id": "synthetic_dialogue_noise_guard::secondary_first_arbitration",
      "chunk_id": null,
      "correct": false,
      "expected_action": "commit_variant",
      "expected_chunk_id": null,
      "expected_variant_id": "synthetic_dialogue_noise_guard::semantic_verified_pruned_e136h_v1",
      "family": "secondary_first_arbitration",
      "selected_proposal_id": "synthetic_dialogue_noise_guard::secondary_first",
      "selected_variant_id": "synthetic_dialogue_noise_guard::legacy_current_e136n",
      "unsafe_commit": false
    },
    {
      "action": "commit_variant",
      "case_id": "synthetic_dialogue_noise_guard::unsafe_direct_write_reject",
      "chunk_id": null,
      "correct": false,
      "expected_action": "commit_variant",
      "expected_chunk_id": null,
      "expected_variant_id": "synthetic_dialogue_noise_guard::semantic_verified_pruned_e136h_v1",
      "family": "unsafe_direct_write_reject",
      "selected_proposal_id": "synthetic_dialogue_noise_guard::unsafe_first",
      "selected_variant_id": "synthetic_dialogue_noise_guard::unsafe_direct_write_control",
      "unsafe_commit": true
    },
    {
      "action": "commit_variant",
      "case_id": "synthetic_dialogue_noise_guard::rollback_on_primary_regression",
      "chunk_id": null,
      "correct": false,
      "expected_action": "commit_variant",
      "expected_chunk_id": null,
      "expected_variant_id": "synthetic_dialogue_noise_guard::legacy_current_e136n",
      "family": "rollback_on_primary_regression",
      "selected_proposal_id": "synthetic_dialogue_noise_guard::regressing_primary",
      "selected_variant_id": "synthetic_dialogue_noise_guard::semantic_verified_pruned_e136h_v1",
      "unsafe_commit": false
    },
    {
      "action": "commit_variant",
      "case_id": "tir_python_block_boundary_lens::clean_primary_first_control",
      "chunk_id": null,
      "correct": true,
      "expected_action": "commit_variant",
      "expected_chunk_id": null,
      "expected_variant_id": "tir_python_block_boundary_lens::current_primary_e136n",
      "family": "clean_primary_first_control",
      "selected_proposal_id": "tir_python_block_boundary_lens::primary_first_control",
      "selected_variant_id": "tir_python_block_boundary_lens::current_primary_e136n",
      "unsafe_commit": false
    },
    {
      "action": "commit_variant",
      "case_id": "tir_python_block_boundary_lens::secondary_first_arbitration",
      "chunk_id": null,
      "correct": false,
      "expected_action": "commit_variant",
      "expected_chunk_id": null,
      "expected_variant_id": "tir_python_block_boundary_lens::current_primary_e136n",
      "family": "secondary_first_arbitration",
      "selected_proposal_id": "tir_python_block_boundary_lens::secondary_first",
      "selected_variant_id": "tir_python_block_boundary_lens::semantic_tightened_trigger_e136h_v1",
      "unsafe_commit": false
    },
    {
      "action": "commit_variant",
      "case_id": "tir_python_block_boundary_lens::unsafe_direct_write_reject",
      "chunk_id": null,
      "correct": false,
      "expected_action": "commit_variant",
      "expected_chunk_id": null,
      "expected_variant_id": "tir_python_block_boundary_lens::current_primary_e136n",
      "family": "unsafe_direct_write_reject",
      "selected_proposal_id": "tir_python_block_boundary_lens::unsafe_first",
      "selected_variant_id": "tir_python_block_boundary_lens::unsafe_direct_write_control",
      "unsafe_commit": true
    },
    {
      "action": "commit_variant",
      "case_id": "tir_python_block_boundary_lens::challenger_hold_child_check",
      "chunk_id": null,
      "correct": false,
      "expected_action": "commit_variant",
      "expected_chunk_id": null,
      "expected_variant_id": "tir_python_block_boundary_lens::current_primary_e136n",
      "family": "challenger_hold_child_check",
      "selected_proposal_id": "tir_python_block_boundary_lens::cheap_challenger_first",
      "selected_variant_id": "tir_python_block_boundary_lens::semantic_tightened_trigger_e136h_v1",
      "unsafe_commit": false
    },
    {
      "action": "commit_variant",
      "case_id": "unit_quantity_binding_lens::clean_primary_first_control",
      "chunk_id": null,
      "correct": true,
      "expected_action": "commit_variant",
      "expected_chunk_id": null,
      "expected_variant_id": "unit_quantity_binding_lens::abstract_current_primary_e136n",
      "family": "clean_primary_first_control",
      "selected_proposal_id": "unit_quantity_binding_lens::primary_first_control",
      "selected_variant_id": "unit_quantity_binding_lens::abstract_current_primary_e136n",
      "unsafe_commit": false
    },
    {
      "action": "commit_variant",
      "case_id": "unit_quantity_binding_lens::secondary_first_arbitration",
      "chunk_id": null,
      "correct": false,
      "expected_action": "commit_variant",
      "expected_chunk_id": null,
      "expected_variant_id": "unit_quantity_binding_lens::abstract_current_primary_e136n",
      "family": "secondary_first_arbitration",
      "selected_proposal_id": "unit_quantity_binding_lens::secondary_first",
      "selected_variant_id": "unit_quantity_binding_lens::abstract_kernel_shadow_e136h_v1",
      "unsafe_commit": false
    },
    {
      "action": "commit_variant",
      "case_id": "unit_quantity_binding_lens::unsafe_direct_write_reject",
      "chunk_id": null,
      "correct": false,
      "expected_action": "commit_variant",
      "expected_chunk_id": null,
      "expected_variant_id": "unit_quantity_binding_lens::abstract_current_primary_e136n",
      "family": "unsafe_direct_write_reject",
      "selected_proposal_id": "unit_quantity_binding_lens::unsafe_first",
      "selected_variant_id": "unit_quantity_binding_lens::unsafe_direct_write_control",
      "unsafe_commit": true
    },
    {
      "action": "commit_variant",
      "case_id": "unit_quantity_binding_lens::lineage_hold_child_check",
      "chunk_id": null,
      "correct": false,
      "expected_action": "commit_variant",
      "expected_chunk_id": null,
      "expected_variant_id": "unit_quantity_binding_lens::abstract_current_primary_e136n",
      "family": "lineage_hold_child_check",
      "selected_proposal_id": "unit_quantity_binding_lens::lineage_candidate_first",
      "selected_variant_id": "unit_quantity_binding_lens::abstract_kernel_shadow_e136h_v1",
      "unsafe_commit": false
    },
    {
      "action": "commit_variant",
      "case_id": "variable_definition_binding_lens::clean_primary_first_control",
      "chunk_id": null,
      "correct": true,
      "expected_action": "commit_variant",
      "expected_chunk_id": null,
      "expected_variant_id": "variable_definition_binding_lens::abstract_current_primary_e136n",
      "family": "clean_primary_first_control",
      "selected_proposal_id": "variable_definition_binding_lens::primary_first_control",
      "selected_variant_id": "variable_definition_binding_lens::abstract_current_primary_e136n",
      "unsafe_commit": false
    },
    {
      "action": "commit_variant",
      "case_id": "variable_definition_binding_lens::secondary_first_arbitration",
      "chunk_id": null,
      "correct": false,
      "expected_action": "commit_variant",
      "expected_chunk_id": null,
      "expected_variant_id": "variable_definition_binding_lens::abstract_current_primary_e136n",
      "family": "secondary_first_arbitration",
      "selected_proposal_id": "variable_definition_binding_lens::secondary_first",
      "selected_variant_id": "variable_definition_binding_lens::abstract_kernel_shadow_e136h_v1",
      "unsafe_commit": false
    },
    {
      "action": "commit_variant",
      "case_id": "variable_definition_binding_lens::unsafe_direct_write_reject",
      "chunk_id": null,
      "correct": false,
      "expected_action": "commit_variant",
      "expected_chunk_id": null,
      "expected_variant_id": "variable_definition_binding_lens::abstract_current_primary_e136n",
      "family": "unsafe_direct_write_reject",
      "selected_proposal_id": "variable_definition_binding_lens::unsafe_first",
      "selected_variant_id": "variable_definition_binding_lens::unsafe_direct_write_control",
      "unsafe_commit": true
    },
    {
      "action": "commit_variant",
      "case_id": "variable_definition_binding_lens::lineage_hold_child_check",
      "chunk_id": null,
      "correct": false,
      "expected_action": "commit_variant",
      "expected_chunk_id": null,
      "expected_variant_id": "variable_definition_binding_lens::abstract_current_primary_e136n",
      "family": "lineage_hold_child_check",
      "selected_proposal_id": "variable_definition_binding_lens::lineage_candidate_first",
      "selected_variant_id": "variable_definition_binding_lens::abstract_kernel_shadow_e136h_v1",
      "unsafe_commit": false
    },
    {
      "action": "commit_variant",
      "case_id": "word_problem_no_solve_guard_v2::clean_primary_first_control",
      "chunk_id": null,
      "correct": true,
      "expected_action": "commit_variant",
      "expected_chunk_id": null,
      "expected_variant_id": "word_problem_no_solve_guard_v2::semantic_verified_pruned_e136h_v1",
      "family": "clean_primary_first_control",
      "selected_proposal_id": "word_problem_no_solve_guard_v2::primary_first_control",
      "selected_variant_id": "word_problem_no_solve_guard_v2::semantic_verified_pruned_e136h_v1",
      "unsafe_commit": false
    },
    {
      "action": "commit_variant",
      "case_id": "word_problem_no_solve_guard_v2::secondary_first_arbitration",
      "chunk_id": null,
      "correct": false,
      "expected_action": "commit_variant",
      "expected_chunk_id": null,
      "expected_variant_id": "word_problem_no_solve_guard_v2::semantic_verified_pruned_e136h_v1",
      "family": "secondary_first_arbitration",
      "selected_proposal_id": "word_problem_no_solve_guard_v2::secondary_first",
      "selected_variant_id": "word_problem_no_solve_guard_v2::legacy_current_e136n",
      "unsafe_commit": false
    },
    {
      "action": "commit_variant",
      "case_id": "word_problem_no_solve_guard_v2::unsafe_direct_write_reject",
      "chunk_id": null,
      "correct": false,
      "expected_action": "commit_variant",
      "expected_chunk_id": null,
      "expected_variant_id": "word_problem_no_solve_guard_v2::semantic_verified_pruned_e136h_v1",
      "family": "unsafe_direct_write_reject",
      "selected_proposal_id": "word_problem_no_solve_guard_v2::unsafe_first",
      "selected_variant_id": "word_problem_no_solve_guard_v2::unsafe_direct_write_control",
      "unsafe_commit": true
    },
    {
      "action": "commit_variant",
      "case_id": "word_problem_no_solve_guard_v2::rollback_on_primary_regression",
      "chunk_id": null,
      "correct": false,
      "expected_action": "commit_variant",
      "expected_chunk_id": null,
      "expected_variant_id": "word_problem_no_solve_guard_v2::legacy_current_e136n",
      "family": "rollback_on_primary_regression",
      "selected_proposal_id": "word_problem_no_solve_guard_v2::regressing_primary",
      "selected_variant_id": "word_problem_no_solve_guard_v2::semantic_verified_pruned_e136h_v1",
      "unsafe_commit": false
    },
    {
      "action": "commit_variant",
      "case_id": "flow_chunk::answer_render_context::01::compatible_chunk",
      "chunk_id": null,
      "correct": false,
      "expected_action": "commit_chunk",
      "expected_chunk_id": "flow_chunk::answer_render_context::01",
      "expected_variant_id": null,
      "family": "compatible_flow_chunk",
      "selected_proposal_id": "answer_format_instruction_lens::chunk_support_1",
      "selected_variant_id": "answer_format_instruction_lens::abstract_current_primary_e136n",
      "unsafe_commit": false
    },
    {
      "action": "commit_variant",
      "case_id": "flow_chunk::assistant_route_context::02::compatible_chunk",
      "chunk_id": null,
      "correct": false,
      "expected_action": "commit_chunk",
      "expected_chunk_id": "flow_chunk::assistant_route_context::02",
      "expected_variant_id": null,
      "family": "compatible_flow_chunk",
      "selected_proposal_id": "assistant_comparison_evaluation_lens::chunk_support_2",
      "selected_variant_id": "assistant_comparison_evaluation_lens::current_primary_e136n",
      "unsafe_commit": false
    },
    {
      "action": "commit_variant",
      "case_id": "flow_chunk::boundary_guard_context::03::compatible_chunk",
      "chunk_id": null,
      "correct": false,
      "expected_action": "commit_chunk",
      "expected_chunk_id": "flow_chunk::boundary_guard_context::03",
      "expected_variant_id": null,
      "family": "compatible_flow_chunk",
      "selected_proposal_id": "assistant_role_turn_boundary_lens::chunk_support_3",
      "selected_variant_id": "assistant_role_turn_boundary_lens::current_primary_e136n",
      "unsafe_commit": false
    },
    {
      "action": "commit_variant",
      "case_id": "flow_chunk::boundary_guard_context::04::compatible_chunk",
      "chunk_id": null,
      "correct": false,
      "expected_action": "commit_chunk",
      "expected_chunk_id": "flow_chunk::boundary_guard_context::04",
      "expected_variant_id": null,
      "family": "compatible_flow_chunk",
      "selected_proposal_id": "geometry_diagram_reference_guard::chunk_support_4",
      "selected_variant_id": "geometry_diagram_reference_guard::semantic_verified_pruned_e136h_v1",
      "unsafe_commit": false
    },
    {
      "action": "commit_variant",
      "case_id": "flow_chunk::boundary_guard_context::05::compatible_chunk",
      "chunk_id": null,
      "correct": false,
      "expected_action": "commit_chunk",
      "expected_chunk_id": "flow_chunk::boundary_guard_context::05",
      "expected_variant_id": null,
      "family": "compatible_flow_chunk",
      "selected_proposal_id": "source_absence_defer_guard::chunk_support_5",
      "selected_variant_id": "source_absence_defer_guard::semantic_verified_pruned_e136h_v1",
      "unsafe_commit": false
    },
    {
      "action": "commit_variant",
      "case_id": "flow_chunk::general_context::06::compatible_chunk",
      "chunk_id": null,
      "correct": false,
      "expected_action": "commit_chunk",
      "expected_chunk_id": "flow_chunk::general_context::06",
      "expected_variant_id": null,
      "family": "compatible_flow_chunk",
      "selected_proposal_id": "fraction_ratio_probability_lens::chunk_support_6",
      "selected_variant_id": "fraction_ratio_probability_lens::abstract_current_primary_e136n",
      "unsafe_commit": false
    },
    {
      "action": "commit_variant",
      "case_id": "flow_chunk::general_context::07::compatible_chunk",
      "chunk_id": null,
      "correct": false,
      "expected_action": "commit_chunk",
      "expected_chunk_id": "flow_chunk::general_context::07",
      "expected_variant_id": null,
      "family": "compatible_flow_chunk",
      "selected_proposal_id": "multi_turn_context_continuity_lens::chunk_support_7",
      "selected_variant_id": "multi_turn_context_continuity_lens::current_primary_e136n",
      "unsafe_commit": false
    },
    {
      "action": "commit_variant",
      "case_id": "flow_chunk::general_context::08::compatible_chunk",
      "chunk_id": null,
      "correct": false,
      "expected_action": "commit_chunk",
      "expected_chunk_id": "flow_chunk::general_context::08",
      "expected_variant_id": null,
      "family": "compatible_flow_chunk",
      "selected_proposal_id": "reasoning_instruction_lens::chunk_support_8",
      "selected_variant_id": "reasoning_instruction_lens::semantic_verified_pruned_e136h_v1",
      "unsafe_commit": false
    },
    {
      "action": "commit_variant",
      "case_id": "flow_chunk::visible_math_context::09::compatible_chunk",
      "chunk_id": null,
      "correct": false,
      "expected_action": "commit_chunk",
      "expected_chunk_id": "flow_chunk::visible_math_context::09",
      "expected_variant_id": null,
      "family": "compatible_flow_chunk",
      "selected_proposal_id": "assistant_math_text_no_solve_guard::chunk_support_9",
      "selected_variant_id": "assistant_math_text_no_solve_guard::current_primary_e136n",
      "unsafe_commit": false
    },
    {
      "action": "commit_variant",
      "case_id": "flow_chunk::visible_math_context::10::compatible_chunk",
      "chunk_id": null,
      "correct": false,
      "expected_action": "commit_chunk",
      "expected_chunk_id": "flow_chunk::visible_math_context::10",
      "expected_variant_id": null,
      "family": "compatible_flow_chunk",
      "selected_proposal_id": "latex_inline_math_boundary_lens::chunk_support_10",
      "selected_variant_id": "latex_inline_math_boundary_lens::semantic_verified_pruned_e136h_v1",
      "unsafe_commit": false
    }
  ]
}
